Workbook

Sheet Executive Summary
B2: Quacked | Financial Model
B4: Prepared for: UGA Kickstart Fund
B5: August 2026
B7: What This Workbook Contains
B8: • Funding Ask Summary — key metrics, founder contribution, funding-use breakdown, and total ask
B9: • Actual Spend to Date — historical costs, sourced from the Anthropic Console and founder-reported subscriptions
B10: • Beta Cost Projection — bottom-up, token-based estimate of API costs for the Sept-Dec 2026 beta window
B11: • Assumptions — every input used across the model, in one editable place
B12: • Roadmap — timeline from today through full launch (Feb. - Mar. 2027)
B14: About Quacked
B15: Quacked is a gamified, drill-style consulting case-interview prep platform built around a full progression of quantitative drill styles — from foundational arithmetic fluency to full case-interview simulation — so learners can enter at whatever stage matches their experience and grow from there. Underneath every mode, a deterministic calculator owns all math and correctness while an AI-generated narrative wrapper owns prose and variation, pairing rigorous accuracy with adaptive, engaging practice at every step of that journey.

Sheet Funding Ask Summary
A2: Funding Summary
A3: All figures link to Actual Spend to Date, Beta Cost Projection, and Assumptions — nothing here is hardcoded.
A5: Key Metrics
A6: Metric | B6: Value | D6: Note
A7: Founder investment to date | B7: ='Actual Spend to Date'!B25 -> 168.15 | D7: Included within the total ask below, not double-counted
A8: Total funding requested | B8: =B31 -> 635.9355 | D8: Covers money already spent + beta-phase operating costs through Dec 2026
A9: Estimated beta users (mid scenario) | B9: ='Beta Cost Projection'!B13 -> 15
A10: Estimated cases generated (mid scenario) | B10: ='Beta Cost Projection'!D13 -> 300
A11: Estimated API cost per case | B11: ='Beta Cost Projection'!B8 -> 0.0159
A12: Beta window covered by this ask | B12: =Assumptions!$B$32&" months" -> 4 months | D12: Sept - Dec 2026
A14: Founder Contribution
A15: Item | B15: Amount | D15: Note
A16: Cash invested to date (API + subscriptions + infra) | B16: ='Actual Spend to Date'!B25 -> 168.15 | D16: Requested for reimbursement as part of the ask below (not additive)
A17: Founder hours invested, not requested for reimbursement | B17: NA | D17: Sweat-equity commitment available upon request
A19: Total spend to date (API + subscriptions + infra) | B19: ='Actual Spend to Date'!B25 -> 168.15
A21: Beta Phase Costs (Sept - Dec 2026, mid scenario)
A22: Item | B22: Cost | D22: Note
A23: Beta API cost (mid scenario: ~15 users x 20 cases) | B23: ='Beta Cost Projection'!E13 -> 4.77 | D23: From Beta Cost Projection tab, mid-scenario column
A24: Infra upgrade (Vercel Pro + Supabase Pro x beta duration) | B24: =(Assumptions!$B$26+Assumptions!$B$27)*Assumptions!$B$32 -> 180 | D24: Needed once beta traffic exceeds free tiers
A25: Subscriptions during beta window (Cursor + Claude + ChatGPT x duration) | B25: =(Assumptions!$B$25+Assumptions!$B$23+Assumptions!$B$24)*Assumptions!$B$32 -> 192 | D25: Dev tool subscriptions held through the beta window
A26: AI content library generation (one-time case pre-generation) | B26: =Assumptions!$B$31 -> 30 | D26: One-time cache-load run before beta
A27: Beta-phase subtotal | B27: =SUM(B23:B26) -> 406.77
A28: Contingency buffer | B28: =B27*Assumptions!$B$33 -> 61.0155 | D28: 15% buffer per Assumptions tab
A29: Beta-phase total (with contingency) | B29: =B27+B28 -> 467.7855
A31: Total Coverage Need | B31: =B19+B29 -> 635.9355
A32: Total Coverage Need = money already spent building through beta + projected cost of running the beta through the Dec 2026 integration window, plus a 15% buffer.
A34: Funding Use Breakdown
A35: Category | B35: Amount | C35: % of Need | D35: Note
A36: AI Infrastructure (Anthropic API, to date + beta) | B36: ='Actual Spend to Date'!B10+'Beta Cost Projection'!E13 -> 8.92 | C36: =B36/$B$31 -> 0.01402658 | D36: Case generation & AI-wrapper calls across Fly, Dive, Swim, Exhibits
A37: Development Tools (Cursor, Claude, ChatGPT subscriptions) | B37: ='Actual Spend to Date'!B19+(Assumptions!$B$25+Assumptions!$B$23+Assumptions!$B$24)*Assumptions!$B$32 -> 356 | C37: =B37/$B$31 -> 0.5598052 | D37: To-date subscriptions + subscriptions held through beta window
A38: Cloud Hosting (Vercel + Supabase) | B38: ='Actual Spend to Date'!B23+(Assumptions!$B$26+Assumptions!$B$27)*Assumptions!$B$32 -> 180 | C38: =B38/$B$31 -> 0.28304757 | D38: Upgrade from free tier once beta traffic requires it
A39: Content Library Generation (one-time) | B39: =Assumptions!$B$31 -> 30 | C39: =B39/$B$31 -> 0.047174596 | D39: Pre-generates Fly + Business Interpretation case pool
A40: Contingency | B40: =B28 -> 61.0155 | C40: =B40/$B$31 -> 0.095946051 | D40: 15% buffer on beta-phase costs
A41: Total Coverage Need | B41: =SUM(B36:B40) -> 635.9355 | C41: =SUM(C36:C40) -> 1

Sheet Actual Spend to Date
A1: Actual Spend to Date
A2: Anthropic API costs pulled directly from the Console cost dashboard. Subscription costs as reported by founder.
A4: Anthropic API Cost (Console)
A5: Period | B5: Cost | C5: Source
A6: May 2026 (May 1 - Jun 1) | B6: 0.04 | C6: Anthropic Console, Cost dashboard, range 2026-05-01 to 2026-06-01
A7: June 2026 (Jun 1 - Jul 1) | B7: 0 | C7: Anthropic Console, Cost dashboard, range 2026-06-01 to 2026-07-01
A8: July 2026 (Jul 1 - Aug 1) | B8: 3.5 | C8: Anthropic Console, Cost dashboard, range 2026-07-01 to 2026-08-01
A9: Aug 2026 (Aug 1 - Aug 8, partial month) | B9: 0.61 | C9: Anthropic Console, Cost dashboard, range 2026-08-01 to 2026-08-08
A10: Total API cost to date | B10: =SUM(B6:B9) -> 4.15
A12: Subscriptions & Dev Tools
A13: Item | B13: Cost | C13: Note
A14: Cursor — June 2026 | B14: 0 | C14: Founder-reported actual
A15: Cursor — July 2026 | B15: 20 | C15: Founder-reported actual (normal usage month)
A16: Cursor — August 2026 | B16: 60 | C16: Founder-reported actual (higher usage month)
A17: Claude subscription, months held x rate | B17: =Assumptions!$B$23*3 -> 60 | C17: Assumes 3 months held at Assumptions rate
A18: ChatGPT subscription, months held x rate | B18: =Assumptions!$B$24*3 -> 24 | C18: Assumes 3 months held at Assumptions rate
A19: Total subscriptions to date | B19: =SUM(B14:B18) -> 164
A21: Infrastructure (Vercel / Supabase)
A22: Item | B22: Cost | C22: Note
A23: Vercel spend to date | B23: 0 | C23: Founder-confirmed: currently on free tiers, $0 to date
A24: Supabase spend to date | B24: 0 | C24: Founder-confirmed: currently on free tiers, $0 to date
A25: TOTAL SPEND TO DATE | B25: =B10+B19+B23 -> 168.15

Sheet Beta Cost Projection
A1: Beta Cost Projection (Sept - Dec 2026)
A2: Every input pulls from the Assumptions tab — change assumptions there, this recalculates.
A4: Cost per API call
A5: Input token cost | B5: =(Assumptions!$B$11/1000000)*Assumptions!$B$6 -> 0.0066
A6: Output token cost | B6: =(Assumptions!$B$12/1000000)*Assumptions!$B$7 -> 0.0093
A7: Cost per API call | B7: =B5+B6 -> 0.0159
A8: Cost per completed case (calls per case x cost per call) | B8: =B7*Assumptions!$B$13 -> 0.0159
A10: Scenario: Beta API Cost by Cohort Size
A11: Scenario | B11: Beta users | C11: Cases / user | D11: Total cases | E11: Total API cost
A12: Low | B12: =Assumptions!$B$17 -> 10 | C12: =Assumptions!$B$19 -> 20 | D12: =B12*C12 -> 200 | E12: =D12*$B$8 -> 3.18
A13: Mid (avg of low/high) | B13: =(Assumptions!$B$17+Assumptions!$B$18)/2 -> 15 | C13: =Assumptions!$B$19 -> 20 | D13: =B13*C13 -> 300 | E13: =D13*$B$8 -> 4.77
A14: High | B14: =Assumptions!$B$18 -> 20 | C14: =Assumptions!$B$19 -> 20 | D14: =B14*C14 -> 400 | E14: =D14*$B$8 -> 6.36
A16: Note: cases-per-user and calls-per-case are founder estimates flagged in Assumptions as unvalidated — treat this as a planning range, not a committed forecast.

Sheet Assumptions
A1: Quacked — Model Assumptions
A2: Update here — everything downstream recalculates.
A4: Anthropic API Pricing (Claude Sonnet 4.5)
A5: Item | B5: Value | C5: Source / Note
A6: Input price ($ per million tokens) | B6: 3 | C6: Anthropic official: anthropic.com/news/claude-sonnet-4-5, verified Aug 2026
A7: Output price ($ per million tokens) | B7: 15 | C7: Anthropic official: anthropic.com/news/claude-sonnet-4-5, verified Aug 2026
A9: Per-Case API Usage
A10: Item | B10: Value | C10: Source / Note
A11: Est. input tokens per API call | B11: 2200 | C11: Pulled from locally stored logs
A12: Est. output tokens per API call | B12: 620 | C12: Pulled from locally stored logs
A13: Est. API calls per completed case | B13: 1 | C13: Pulled from locally stored logs
A15: Beta Cohort Assumptions
A16: Item | B16: Value | C16: Source / Note
A17: Beta cohort size — low | B17: 10 | C17: Founder estimate: 10-20 person beta, mixed recruiting-experience/no-experience for varied feedback
A18: Beta cohort size — high | B18: 20 | C18: Founder estimate
A19: Est. cases per beta user | B19: 20 | C19: Founder estimate, flagged as uncertain — validate against actual beta usage once live
A21: Non-API Recurring Costs
A22: Item | B22: Value ($/mo) | C22: Source / Note
A23: Claude subscription (Pro) | B23: 20
A24: ChatGPT subscription (Go) | B24: 8
A25: Cursor — ongoing monthly rate | B25: 20 | C25: Founder-confirmed: resets to $20/mo going forward (June was $20, Aug was $60 — see Actual Spend tab)
A26: Vercel Pro (post-beta-scale) | B26: 20 | C26: Vercel official pricing, per seat/mo, verified Aug 2026
A27: Supabase Pro (post-beta-scale) | B27: 25 | C27: Supabase official pricing, base/mo (usage overages not included), verified Aug 2026
A29: One-Time / Beta-Window Costs
A30: Item | B30: Value | C30: Source / Note
A31: Library build day (case pre-generation; cache loading) | B31: 30 | C31: Founder estimate
A32: Approx. beta + testing window duration (months) | B32: 4
A33: Contingency / buffer | B33: 0.15

Sheet Roadmap
A1: Roadmap — Beta Through Full Launch
A2: Target dates as of Aug 2026. Status column is a manual field — update as milestones complete.
A4: Milestone | B4: Target Date | C4: Notes
A5: Content Quality Enhancement | B5: In progress, August 2026
A6: Realistic Case-Interview Simulation | B6: In progress, August 2026
A7: AI Content Library Generation — pre-generate case content | B7: In progress, August 2026
A8: UI/UX + Landing Polish | B8: Before beta invites
A9: Beta invites go out | B9: By September 1, 2026 (latest) | C9: 10-20 person cohort, mixed recruiting-experience/no-experience
A10: Beta feedback integration window opens | B10: By December 1, 2026 (latest)
A11: Beta feedback integration window closes | B11: By December 31, 2026 (latest) | C11: Feedback fully integrated over winter break
A12: Second brief beta sprint + pricing strategy session | B12: Early 2027 | C12: Informs final pricing model and recruiting-sprint bundle decisions
A13: Recruiting sprint bundles & early pricing model finalized | B13: Early 2027, before full launch
A14: Full public launch | B14: February - March 2027
