Workbook

Sheet Assumptions
A1: Quacked — Model Assumptions (edit the blue cells)
A2: All cells in blue are editable inputs. Black cells are formulas that pull from these. Update here — everything downstream recalculates.
A4: Anthropic API Pricing (Claude Sonnet 4.5)
A5: Item | B5: Value | C5: Source / Note
A6: Input price ($ per million tokens) | B6: 3 | C6: Anthropic official: anthropic.com/news/claude-sonnet-4-5, verified Aug 2026
A7: Output price ($ per million tokens) | B7: 15 | C7: Same source
A9: Per-Case API Usage Estimate (PLACEHOLDER — refine once real usage logs exist)
A10: Item | B10: Value | C10: Source / Note
A11: Est. input tokens per API call | B11: 3000 | C11: Placeholder estimate (system prompt + case context). Refine from actual token logs.
A12: Est. output tokens per API call | B12: 1000 | C12: Placeholder estimate (generated case/feedback prose). Refine from actual token logs.
A13: Est. API calls per completed case | B13: 2 | C13: Placeholder — e.g. one generation call + one prose/interpretation call. Varies by engine (Fly, Dive, Swim, Exhibits).
A15: Beta Cohort Assumptions
A16: Item | B16: Value | C16: Source / Note
A17: Beta cohort size — low | B17: 10 | C17: Founder estimate: 10-20 person beta, mixed recruiting-experience/no-experience for varied feedback
A18: Beta cohort size — high | B18: 20 | C18: Founder estimate
A19: Est. cases per beta user | B19: 20 | C19: Founder estimate, flagged as uncertain — validate against actual beta usage once live
A21: Non-API Recurring Costs
A22: Item | B22: Value ($/mo) | C22: Source / Note
A23: Claude subscription (Pro/Max) | B23: 20 | C23: PLACEHOLDER — confirm exact plan & monthly cost
A24: ChatGPT subscription (Go tier) | B24: 20 | C24: PLACEHOLDER — confirm exact plan & monthly cost
A25: Cursor — ongoing monthly rate | B25: 20 | C25: Founder-confirmed: resets to $20/mo going forward (June was $20, Aug was $60 — see Actual Spend tab)
A26: Vercel Pro (post-beta-scale) | B26: 20 | C26: Vercel official pricing, per seat/mo, verified Aug 2026
A27: Supabase Pro (post-beta-scale) | B27: 25 | C27: Supabase official pricing, base/mo (usage overages not included), verified Aug 2026
A29: One-Time / Beta-Window Costs
A30: Item | B30: Value | C30: Source / Note
A31: Library build day (case pre-generation) | B31: 30
A32: Beta + testing window duration (months) | B32: 4
A33: Contingency / buffer | B33: 0.15

Sheet Actual Spend to Date
A1: Actual Spend to Date
A2: Anthropic API costs pulled directly from the Console cost dashboard. Subscription costs as reported by founder.
A4: Anthropic API Cost (Console)
A5: Period | B5: Cost | C5: Source
A6: May 2026 (May 1 - Jun 1) | B6: 0.04 | C6: Anthropic Console, Cost dashboard, range 2026-05-01 to 2026-06-01
A7: June 2026 (Jun 1 - Jul 1) | B7: 0 | C7: Anthropic Console, Cost dashboard, range 2026-06-01 to 2026-07-01
A8: July 2026 (Jul 1 - Aug 1) | B8: 3.5 | C8: Anthropic Console, Cost dashboard, range 2026-07-01 to 2026-08-01
A9: Aug 2026 (Aug 1 - Aug 8, partial month) | B9: 0.61 | C9: Anthropic Console, Cost dashboard, range 2026-08-01 to 2026-08-08
A10: Total API cost to date | B10: =SUM(B6:B9) -> 4.15
A12: Subscriptions & Dev Tools
A13: Item | B13: Cost | C13: Note
A14: Cursor — June 2026 | B14: 0 | C14: Founder-reported actual
A15: Cursor — July 2026 | B15: 20 | C15: NEEDS FOUNDER — amount not specified; enter actual or estimate
A16: Cursor — August 2026 | B16: 60 | C16: Founder-reported actual (higher usage month)
A17: Claude subscription, months held x rate | B17: =Assumptions!$B$23*3 -> 60 | C17: PLACEHOLDER: assumes 3 months held at Assumptions rate — confirm actual start date & plan
A18: ChatGPT subscription, months held x rate | B18: =Assumptions!$B$24*3 -> 60 | C18: PLACEHOLDER: assumes 3 months held at Assumptions rate — confirm actual start date & plan
A19: Total subscriptions to date (excl. TBD items) | B19: =SUM(B14:B18) -> 200
A21: Infrastructure (Vercel / Supabase)
A22: Item | B22: Cost | C22: Note
A23: Vercel / Supabase spend to date | B23: 0 | C23: Founder-confirmed: currently on free tiers, $0 to date
A25: TOTAL SPEND TO DATE (excl. TBD items above) | B25: =B10+B19+B23 -> 204.15

Sheet Beta Cost Projection
A1: Beta Cost Projection (Sept - Dec 2026)
A2: Bottom-up token-based estimate. Every input pulls from the Assumptions tab — change assumptions there, this recalculates.
A4: Cost per API call
A5: Input token cost | B5: =(Assumptions!$B$11/1000000)*Assumptions!$B$6 -> 0.009
A6: Output token cost | B6: =(Assumptions!$B$12/1000000)*Assumptions!$B$7 -> 0.015
A7: Cost per API call | B7: =B5+B6 -> 0.024
A8: Cost per completed case (calls per case x cost per call) | B8: =B7*Assumptions!$B$13 -> 0.048
A10: Scenario: Beta API Cost by Cohort Size
A11: Scenario | B11: Beta users | C11: Cases / user | D11: Total cases | E11: Total API cost
A12: Low | B12: =Assumptions!$B$17 -> 10 | C12: =Assumptions!$B$19 -> 20 | D12: =B12*C12 -> 200 | E12: =D12*$B$8 -> 9.6
A13: Mid (avg of low/high) | B13: =(Assumptions!$B$17+Assumptions!$B$18)/2 -> 15 | C13: =Assumptions!$B$19 -> 20 | D13: =B13*C13 -> 300 | E13: =D13*$B$8 -> 14.4
A14: High | B14: =Assumptions!$B$18 -> 20 | C14: =Assumptions!$B$19 -> 20 | D14: =B14*C14 -> 400 | E14: =D14*$B$8 -> 19.2
A16: Note: cases-per-user and calls-per-case are founder estimates flagged in Assumptions as unvalidated — treat this as a planning range, not a committed forecast.

Sheet Funding Ask Summary
A1: Funding Ask Summary
A2: Combines actual spend to date with projected beta-phase costs (mid scenario) to justify the total ask.
A4: Already Spent (to date)
A5: Total spend to date (API + subscriptions + infra) | B5: ='Actual Spend to Date'!B25 -> 204.15
A7: Beta Phase Costs (Sept - Dec 2026, mid scenario)
A8: Item | B8: Cost | C8: Note
A9: Beta API cost (mid scenario: ~15 users x 20 cases) | B9: ='Beta Cost Projection'!E13 -> 14.4 | C9: From Beta Cost Projection tab, mid-scenario column
A10: Infra upgrade (Vercel Pro + Supabase Pro x beta duration) | B10: =(Assumptions!$B$26+Assumptions!$B$27)*Assumptions!$B$32 -> 180 | C10: Needed once beta traffic exceeds free tiers
A11: Subscriptions during beta window (Cursor + Claude + ChatGPT x duration) | B11: =(Assumptions!$B$25+Assumptions!$B$23+Assumptions!$B$24)*Assumptions!$B$32 -> 240 | C11: Dev tool subscriptions held through the beta window
A12: Library build day (case pre-generation) | B12: =Assumptions!$B$31 -> 30 | C12: One-time cache-load run before beta
A13: Beta-phase subtotal | B13: =SUM(B9:B12) -> 464.4
A14: Contingency buffer | B14: =B13*Assumptions!$B$33 -> 69.66 | C14: 15% buffer per Assumptions tab
A15: Beta-phase total (with contingency) | B15: =B13+B14 -> 534.06
A17: TOTAL FUNDING ASK | B17: =B5+B15 -> 738.21
A18: Total funding ask = money already spent building through beta + projected cost of running the beta through the Dec 2026 integration window, plus a 15% buffer.

Sheet Roadmap & Milestones
A1: Pro Forma Roadmap — Beta Through Full Launch
A2: Target dates as of Aug 2026. Status column is a manual field — update as milestones complete.
A4: Milestone | B4: Target Date | C4: Notes
A5: Exhibits Batch 4.5 (content remediation) | B5: In progress, Aug 2026 | C5: Precedes Batch 5 archetypes; scoped, not yet built
A6: Fly Phase B (real UI/UX build) | B6: Fall 2026 | C6: Builds on completed Phase A engine extraction
A7: Case library build day (pre-generate Fly + Business Interpretation cases) | B7: Before beta invites | C7: Avoids per-user on-demand API spend at scale; sequenced after Fly Phase B
A8: Stripe integration, QA pass, custom domain | B8: Before beta invites | C8: Domain/webhooks deferred to just before invites per existing plan
A9: Beta invites go out | B9: September 2026 | C9: 10-20 person cohort, mixed recruiting-experience/no-experience
A10: Beta feedback integration window opens | B10: By December 1, 2026 (latest)
A11: Beta feedback integration window closes | B11: December 31, 2026 | C11: Feedback fully integrated over winter break
A12: Second brief beta sprint + pricing strategy session | B12: Early 2027 | C12: Informs final pricing model and recruiting-sprint bundle decisions
A13: Recruiting sprint bundles & early pricing model finalized | B13: Early 2027, before full launch
A14: Full public launch | B14: January - February 2027
